currencies/__init__.py
currencies/config.py
currencies/exceptions.py
tests/__init__.py
tests/test_currency.py
currencies-2020.12.12.dist-info/AUTHORS.rst
currencies-2020.12.12.dist-info/LICENSE
currencies-2020.12.12.dist-info/METADATA
currencies-2020.12.12.dist-info/WHEEL
currencies-2020.12.12.dist-info/top_level.txt
currencies-2020.12.12.dist-info/RECORD
