Metadata-Version: 1.2
Name: currencies
Version: 2020.12.12
Summary: Display money format and its filthy currencies, for all money lovers out there.
Home-page: https://github.com/Alir3z4/python-currencies
Author: Alireza Savand
Author-email: alireza.savand@gmail.com
License: GNU GPL 3
Platform: UNKNOWN
Classifier: Development Status :: 5 - Production/Stable
Classifier: Intended Audience :: Developers
Classifier: License :: OSI Approved :: GNU General Public License (GPL)
Classifier: Operating System :: OS Independent
Classifier: Programming Language :: Python
Classifier: Programming Language :: Python :: 3
Classifier: Programming Language :: Python :: 3.8
Classifier: Topic :: Software Development
Requires-Python: <4
